statmoments/__init__.py
statmoments/_native.c
statmoments/_native.cpython-310-darwin.so
statmoments/_native_shim.py
statmoments/_statmoments_impl.py
statmoments/_version.py
statmoments/bivar.py
statmoments/common.py
statmoments/stattests.py
statmoments/univar.py
statmoments/benchmark/__init__.py
statmoments/benchmark/__main__.py
statmoments/benchmark/bench_bivar.py
statmoments/benchmark/benchlib.py
statmoments/tests/__init__.py
statmoments/tests/__main__.py
statmoments/tests/test_bivar.py
statmoments/tests/test_common.py
statmoments/tests/test_connect.py
statmoments/tests/test_stattest.py
statmoments/tests/test_univar.py
statmoments-1.1.1.dist-info/LICENSE
statmoments-1.1.1.dist-info/METADATA
statmoments-1.1.1.dist-info/WHEEL
statmoments-1.1.1.dist-info/top_level.txt
statmoments-1.1.1.dist-info/RECORD
