Metadata-Version: 2.2
Name: statmoments
Version: 1.1.1
Summary: Streaming statistical moments
Author: Anton Kochepasov
Author-email: akss@me.com
License: MIT License
Project-URL: Source Code, https://github.com/akochepasov/statmoments/
Project-URL: Issues, https://github.com/akochepasov/statmoments/issues
Keywords: data-science,univariate,bivariate,statistics,streaming,numpy,vectorization
Platform: any
Classifier: Development Status :: 5 - Production/Stable
Classifier: Environment :: Console
Classifier: Intended Audience :: Science/Research
Classifier: Intended Audience :: Financial and Insurance Industry
Classifier: License :: OSI Approved :: MIT License
Classifier: Operating System :: OS Independent
Classifier: Programming Language :: Cython
Classifier: Programming Language :: Python
Classifier: Programming Language :: Python :: 3
Classifier: Programming Language :: Python :: 3.6
Classifier: Programming Language :: Python :: 3.7
Classifier: Programming Language :: Python :: 3.8
Classifier: Programming Language :: Python :: 3.9
Classifier: Programming Language :: Python :: 3.10
Classifier: Programming Language :: Python :: 3.11
Classifier: Programming Language :: Python :: 3.12
Classifier: Topic :: Scientific/Engineering :: Artificial Intelligence
Classifier: Topic :: Scientific/Engineering :: Image Processing
Classifier: Topic :: Scientific/Engineering :: Information Analysis
Classifier: Topic :: Scientific/Engineering :: Mathematics
Classifier: Topic :: Scientific/Engineering :: Physics
Requires-Python: >=3.6
Requires-Dist: numpy<2,>=1.17
Requires-Dist: scipy<=1.15
Requires-Dist: h5py
Requires-Dist: psutil
Requires-Dist: cython
